[
    {
        "prod_id": null,
        "name": "앱코 G40 시그니처 (블랙)",
        "price": 49900,
        "specs": [
            "PC케이스(ATX)",
            "미들타워",
            "파워미포함",
            "ATX",
            "M-ATX",
            "ITX",
            "쿨링팬:총4개",
            "LED팬:4개",
            "전면 패널 타입:메쉬",
            "측면 패널 타입:강화유리",
            "측면 개폐 방식:스윙도어",
            "후면:140mm LED x1",
            "전면:140mm LED x3",
            "너비(W):230mm",
            "깊이(D):410mm",
            "높이(H):485mm",
            "파워 장착 길이:178mm",
            "파워 위치:하단후면",
            "VGA 장착 길이:340mm",
            "CPU쿨러 장착높이:175mm",
            "외부LED 컨트롤",
            "LED 색상:RGB"
        ],
        "danawa_href": "https://shop.danawa.com/main/?controller=goods&methods=index&productRegisterAreaGroupSeq=78&serviceSectionSeq=600#",
        "image_url": "https://img.danawa.com/prod_img/500000/727/900/img/16900727_1.jpg",
        "registration_date": "등록월 2022.04."
    },
    {
        "prod_id": 53783243,
        "name": "앱코 U30 마린 (블랙)",
        "price": 37900,
        "specs": [
            "PC케이스(ATX)",
            "미들타워",
            "파워미포함",
            "ATX",
            "M-ATX",
            "M-ITX",
            "쿨링팬:총3개",
            "LED팬:3개",
            "전면 패널 타입:강화유리",
            "측면 패널 타입:강화유리",
            "측면 개폐 방식:버튼",
            "후면:120mm LED x1",
            "내부 측면:120mm LED x2",
            "너비(W):212mm",
            "깊이(D):420mm",
            "높이(H):485mm",
            "파워 장착 길이:240mm",
            "파워 위치:하단후면",
            "VGA 장착 길이:400mm",
            "CPU쿨러 장착높이:165mm",
            "LED 색상:RGB"
        ],
        "danawa_href": "https://shop.danawa.com/main/?controller=goods&methods=blog&billingInternalProductSeq=53783243&productRegisterAreaGroupSeq=78&serviceSectionSeq=600",
        "image_url": "https://img.danawa.com/prod_img/500000/243/783/img/53783243_1.jpg",
        "registration_date": "등록월 2024.05"
    },
    {
        "prod_id": 56138000,
        "name": "앱코 U20M 큐빅 미니 (블랙)",
        "price": 30720,
        "specs": [
            "PC케이스(M-ATX)",
            "미니타워",
            "파워미포함",
            "M-ATX",
            "M-ITX",
            "쿨링팬:총3개",
            "LED팬:3개",
            "전면 패널 타입:강화유리",
            "측면 패널 타입:강화유리",
            "측면 개폐 방식:버튼",
            "후면:120mm LED x1",
            "내부 측면:120mm LED x2",
            "너비(W):212mm",
            "깊이(D):360mm",
            "높이(H):435mm",
            "파워 장착 길이:350mm",
            "파워 위치:하단후면",
            "VGA 장착 길이:350mm",
            "CPU쿨러 장착높이:165mm",
            "LED 색상:RGB"
        ],
        "danawa_href": "https://shop.danawa.com/main/?controller=goods&methods=blog&billingInternalProductSeq=56138000&productRegisterAreaGroupSeq=78&serviceSectionSeq=600",
        "image_url": "https://img.danawa.com/prod_img/500000/000/138/img/56138000_1.jpg",
        "registration_date": "등록월 2024.06"
    },
    {
        "prod_id": 16900727,
        "name": "앱코 G40 시그니처 (블랙)",
        "price": 49900,
        "specs": [
            "PC케이스(ATX)",
            "미들타워",
            "파워미포함",
            "ATX",
            "M-ATX",
            "ITX",
            "쿨링팬:총4개",
            "LED팬:4개",
            "전면 패널 타입:메쉬",
            "측면 패널 타입:강화유리",
            "측면 개폐 방식:스윙도어",
            "후면:140mm LED x1",
            "전면:140mm LED x3",
            "너비(W):230mm",
            "깊이(D):410mm",
            "높이(H):485mm",
            "파워 장착 길이:178mm",
            "파워 위치:하단후면",
            "VGA 장착 길이:340mm",
            "CPU쿨러 장착높이:175mm",
            "외부LED 컨트롤",
            "LED 색상:RGB"
        ],
        "danawa_href": "https://shop.danawa.com/main/?controller=goods&methods=blog&billingInternalProductSeq=16900727&productRegisterAreaGroupSeq=78&serviceSectionSeq=600",
        "image_url": "https://img.danawa.com/prod_img/500000/727/900/img/16900727_1.jpg",
        "registration_date": "등록월 2022.04"
    },
    {
        "prod_id": 28058570,
        "name": "앱코 G15 세이퍼 아크릴 (블랙)",
        "price": 32900,
        "specs": [
            "PC케이스(ATX)",
            "미들타워",
            "파워미포함",
            "ATX",
            "M-ATX",
            "M-ITX",
            "쿨링팬:총4개",
            "LED팬:4개",
            "전면 패널 타입:메쉬",
            "측면 패널 타입:아크릴",
            "후면:120mm LED X1",
            "전면:120mm LED X3",
            "너비(W):205mm",
            "깊이(D):350mm",
            "높이(H):445mm",
            "파워 장착 길이:140~150mm",
            "파워 위치:하단후면",
            "VGA 장착 길이:300mm",
            "CPU쿨러 장착높이:160mm",
            "23년 10월 ssd 최대 3개 장착 → 2개로 변경"
        ],
        "danawa_href": "https://shop.danawa.com/main/?controller=goods&methods=blog&billingInternalProductSeq=28058570&productRegisterAreaGroupSeq=78&serviceSectionSeq=600",
        "image_url": "https://img.danawa.com/prod_img/500000/570/058/img/28058570_1.jpg",
        "registration_date": "등록월 2023.09."
    },
    {
        "prod_id": 18212909,
        "name": "DAVEN D6 MESH 강화유리 (블랙)",
        "price": 39900,
        "specs": [
            "PC케이스(ATX)",
            "미들타워",
            "파워미포함",
            "ATX",
            "M-ATX",
            "M-ITX",
            "쿨링팬:총6개",
            "LED팬:4개",
            "전면 패널 타입:메쉬",
            "측면 패널 타입:강화유리",
            "후면:120mm LED x1",
            "전면:120mm LED x3",
            "상단:120mm x2",
            "너비(W):216mm",
            "깊이(D):366mm",
            "높이(H):463mm",
            "파워 장착 길이:170~250mm",
            "파워 위치:하단후면",
            "VGA 장착 길이:330mm",
            "CPU쿨러 장착높이:173mm",
            "RGB 컨트롤",
            "LED 색상:RGB"
        ],
        "danawa_href": "https://shop.danawa.com/main/?controller=goods&methods=blog&billingInternalProductSeq=18212909&productRegisterAreaGroupSeq=78&serviceSectionSeq=600",
        "image_url": "https://img.danawa.com/prod_img/500000/909/212/img/18212909_1.jpg",
        "registration_date": "등록월 2022.11."
    },
    {
        "prod_id": 18419840,
        "name": "BRAVOTEC GUARDIAN 3100M V2 타이탄 글래스 (블랙)",
        "price": 89000,
        "specs": [
            "PC케이스(ATX)",
            "빅타워",
            "파워미포함",
            "E-ATX",
            "ATX",
            "M-ATX",
            "M-ITX",
            "수직 PCI형태:기본형",
            "쿨링팬:총4개",
            "LED팬:4개",
            "전면 패널 타입:메쉬",
            "측면 패널 타입:강화유리",
            "너비(W):245mm",
            "깊이(D):464mm",
            "높이(H):494mm",
            "파워 장착 길이:280~380mm",
            "파워 위치:하단후면",
            "VGA 장착 길이:380mm",
            "CPU쿨러 장착높이:180mm",
            "RGB 컨트롤",
            "LED 색상:ARGB",
            "E-ATX 최대 290mm 지원 / 팬허브 포함 / 23년 3월 → 그래픽 카드 지지대 기본 제공"
        ],
        "danawa_href": "https://shop.danawa.com/main/?controller=goods&methods=blog&billingInternalProductSeq=18419840&productRegisterAreaGroupSeq=78&serviceSectionSeq=600",
        "image_url": "https://img.danawa.com/prod_img/500000/840/419/img/18419840_1.jpg",
        "registration_date": "등록월 2022.12."
    },
    {
        "prod_id": 32861099,
        "name": "darkFlash DS900 ARGB 강화유리 (블랙)",
        "price": 55000,
        "specs": [
            "PC케이스(ATX)",
            "미들타워",
            "파워미포함",
            "ATX",
            "M-ATX",
            "M-ITX",
            "쿨링팬:총4개",
            "LED팬:4개",
            "전면 패널 타입:강화유리",
            "측면 패널 타입:강화유리",
            "후면:120mm LED x1",
            "내부 측면:120mm LED x3",
            "너비(W):218mm",
            "깊이(D):434mm",
            "높이(H):454mm",
            "파워 장착 길이:260mm",
            "파워 위치:하단후면",
            "VGA 장착 길이:425mm",
            "CPU쿨러 장착높이:170mm",
            "LED 색상:ARGB",
            "24년 4월 장착쿨링팬 C6 ARGB → C7 ARGB으로 변경 / 24년 8월 상단 라디에이터 120, 140, 240, 280, 360 →120, 240, 360으로 변경"
        ],
        "danawa_href": "https://shop.danawa.com/main/?controller=goods&methods=blog&billingInternalProductSeq=32861099&productRegisterAreaGroupSeq=78&serviceSectionSeq=600",
        "image_url": "https://img.danawa.com/prod_img/500000/099/861/img/32861099_1.jpg",
        "registration_date": "등록월 2024.01."
    },
    {
        "prod_id": 68440877,
        "name": "darkFlash DY470 ARGB 강화유리 (화이트)",
        "price": 129000,
        "specs": [
            "PC케이스(ATX)",
            "미들타워",
            "파워미포함",
            "ATX",
            "ATX (후면커넥터)",
            "M-ATX",
            "M-ITX",
            "쿨링팬:총4개",
            "LED팬:4개",
            "전면 패널 타입:강화유리",
            "측면 패널 타입:강화유리",
            "후면:120mm LED x1",
            "내부 측면:120mm LED x3",
            "너비(W):298mm",
            "깊이(D):473mm",
            "높이(H):497mm",
            "VGA 장착 길이:410mm",
            "CPU쿨러 장착높이:175mm",
            "LED 색상:ARGB"
        ],
        "danawa_href": "https://shop.danawa.com/main/?controller=goods&methods=blog&billingInternalProductSeq=68440877&productRegisterAreaGroupSeq=78&serviceSectionSeq=600",
        "image_url": "https://img.danawa.com/prod_img/500000/877/440/img/68440877_1.jpg",
        "registration_date": "등록월 2024.10."
    },
    {
        "prod_id": 48648926,
        "name": "마이크로닉스 COOLMAX 스테디 (블랙)",
        "price": 43900,
        "specs": [
            "PC케이스(ATX)",
            "미들타워",
            "파워미포함",
            "ATX",
            "M-ATX",
            "M-ITX",
            "쿨링팬:총4개",
            "LED팬:4개",
            "전면 패널 타입:메쉬",
            "측면 패널 타입:강화유리",
            "측면 개폐 방식:버튼",
            "후면:120mm LED x1",
            "전면:140mm LED x3",
            "너비(W):215mm",
            "깊이(D):400mm",
            "높이(H):470mm",
            "파워 위치:하단후면",
            "VGA 장착 길이:355mm",
            "CPU쿨러 장착높이:165mm",
            "RGB 컨트롤",
            "LED 색상:RGB"
        ],
        "danawa_href": "https://shop.danawa.com/main/?controller=goods&methods=blog&billingInternalProductSeq=48648926&productRegisterAreaGroupSeq=78&serviceSectionSeq=600",
        "image_url": "https://img.danawa.com/prod_img/500000/926/648/img/48648926_1.jpg",
        "registration_date": "등록월 2024.04."
    },
    {
        "prod_id": 31286447,
        "name": "3RSYS R640 Quiet (블랙)",
        "price": 89280,
        "specs": [
            "PC케이스(ATX)",
            "미들타워",
            "파워미포함",
            "ATX",
            "M-ATX",
            "ITX",
            "쿨링팬:총4개",
            "LED팬:4개",
            "전면 패널 타입:메쉬",
            "측면 패널 타입:강화유리",
            "측면 개폐 방식:스윙도어",
            "후면:140mm LED x1",
            "전면:140mm LED x3",
            "너비(W):230mm",
            "깊이(D):460mm",
            "높이(H):492mm",
            "파워 장착 길이:230mm",
            "파워 위치:하단후면",
            "VGA 장착 길이:400mm",
            "CPU쿨러 장착높이:179mm",
            "팬 컨트롤",
            "LED 색상:ARGB"
        ],
        "danawa_href": "https://shop.danawa.com/main/?controller=goods&methods=blog&billingInternalProductSeq=31286447&productRegisterAreaGroupSeq=78&serviceSectionSeq=600",
        "image_url": "https://img.danawa.com/prod_img/500000/447/286/img/31286447_1.jpg",
        "registration_date": "등록월 2023.12."
    },
    {
        "prod_id": 64392029,
        "name": "앱코 U40M 웨일샤크 ARGB BTF (블랙)",
        "price": 49900,
        "specs": [
            "PC케이스(M-ATX)",
            "미니타워",
            "파워미포함",
            "M-ATX",
            "M-ATX (후면커넥터)",
            "M-ITX",
            "쿨링팬:총3개",
            "LED팬:3개",
            "전면 패널 타입:강화유리",
            "측면 패널 타입:강화유리",
            "측면 개폐 방식:버튼",
            "후면:120mm LED x1",
            "내부 측면:120mm LED x2",
            "너비(W):218mm",
            "깊이(D):420mm",
            "높이(H):395mm",
            "파워 장착 길이:240mm",
            "파워 위치:하단후면",
            "VGA 장착 길이:410mm",
            "CPU쿨러 장착높이:160mm",
            "LED 색상:ARGB"
        ],
        "danawa_href": "https://shop.danawa.com/main/?controller=goods&methods=blog&billingInternalProductSeq=64392029&productRegisterAreaGroupSeq=78&serviceSectionSeq=600",
        "image_url": "https://img.danawa.com/prod_img/500000/029/392/img/64392029_1.jpg",
        "registration_date": "등록월 2024.08."
    },
    {
        "prod_id": 17409059,
        "name": "3RSYS L600 Quiet (블랙)",
        "price": 87290,
        "specs": [
            "PC케이스(ATX)",
            "미들타워",
            "파워미포함",
            "E-ATX",
            "ATX",
            "M-ATX",
            "ITX",
            "수직 PCI형태:기본형",
            "쿨링팬:총4개",
            "전면 패널 타입:메쉬",
            "측면 패널 타입:강화유리",
            "측면 개폐 방식:스윙도어",
            "후면:140mm x1",
            "전면:140mm x3",
            "너비(W):233mm",
            "깊이(D):484mm",
            "높이(H):487mm",
            "파워 장착 길이:200mm",
            "파워 위치:하단후면",
            "VGA 장착 길이:400mm",
            "CPU쿨러 장착높이:180mm",
            "E-ATX 최대 길이 277mm / 우측 패널 타공 / 팬허브 기본 제공"
        ],
        "danawa_href": "https://shop.danawa.com/main/?controller=goods&methods=blog&billingInternalProductSeq=17409059&productRegisterAreaGroupSeq=78&serviceSectionSeq=600",
        "image_url": "https://img.danawa.com/prod_img/500000/059/409/img/17409059_1.jpg",
        "registration_date": "등록월 2022.07."
    },
    {
        "prod_id": 32861129,
        "name": "darkFlash DS900 ARGB 강화유리 (화이트)",
        "price": 59000,
        "specs": [
            "PC케이스(ATX)",
            "미들타워",
            "파워미포함",
            "ATX",
            "M-ATX",
            "M-ITX",
            "쿨링팬:총4개",
            "LED팬:4개",
            "전면 패널 타입:강화유리",
            "측면 패널 타입:강화유리",
            "후면:120mm LED x1",
            "내부 측면:120mm LED x3",
            "너비(W):218mm",
            "깊이(D):434mm",
            "높이(H):454mm",
            "파워 장착 길이:260mm",
            "파워 위치:하단후면",
            "VGA 장착 길이:425mm",
            "CPU쿨러 장착높이:170mm",
            "LED 색상:ARGB",
            "24년 4월 장착쿨링팬 C6 ARGB → C7 ARGB으로 변경 / 24년 8월 상단 라디에이터 120, 140, 240, 280, 360 →120, 240, 360으로 변경"
        ],
        "danawa_href": "https://shop.danawa.com/main/?controller=goods&methods=blog&billingInternalProductSeq=32861129&productRegisterAreaGroupSeq=78&serviceSectionSeq=600",
        "image_url": "https://img.danawa.com/prod_img/500000/129/861/img/32861129_1.jpg",
        "registration_date": "등록월 2024.01."
    },
    {
        "prod_id": 32104556,
        "name": "DAVEN AQUARIUM (화이트)",
        "price": 56800,
        "specs": [
            "PC케이스(ATX)",
            "미들타워",
            "파워미포함",
            "ATX",
            "ATX (후면커넥터)",
            "M-ATX",
            "M-ATX (후면커넥터)",
            "ITX",
            "쿨링팬:총4개",
            "LED팬:4개",
            "전면 패널 타입:강화유리",
            "측면 패널 타입:강화유리",
            "후면:120mm LED x1",
            "내부 측면:120mm LED x3",
            "너비(W):285mm",
            "깊이(D):425mm",
            "높이(H):395mm",
            "파워 장착 길이:200mm",
            "파워 위치:상단",
            "VGA 장착 길이:415mm",
            "CPU쿨러 장착높이:163mm",
            "LED 색상:ARGB"
        ],
        "danawa_href": "https://shop.danawa.com/main/?controller=goods&methods=blog&billingInternalProductSeq=32104556&productRegisterAreaGroupSeq=78&serviceSectionSeq=600",
        "image_url": "https://img.danawa.com/prod_img/500000/556/104/img/32104556_1.jpg",
        "registration_date": "등록월 2024.01."
    },
    {
        "prod_id": 11884168,
        "name": "darkFlash DLX21 RGB MESH 강화유리 (블랙)",
        "price": 98000,
        "specs": [
            "PC케이스(ATX)",
            "미들타워",
            "파워미포함",
            "E-ATX",
            "ATX",
            "M-ATX",
            "M-ITX",
            "쿨링팬:총4개",
            "LED팬:4개",
            "측면 패널 타입:강화유리",
            "측면 개폐 방식:스윙도어",
            "후면:140mm LED x1",
            "전면:140mm LED x3",
            "너비(W):233mm",
            "깊이(D):448mm",
            "높이(H):493mm",
            "파워 장착 길이:235mm",
            "파워 위치:하단후면",
            "VGA 장착 길이:400mm",
            "CPU쿨러 장착높이:180mm",
            "RGB 컨트롤",
            "LED 색상:RGB"
        ],
        "danawa_href": "https://shop.danawa.com/main/?controller=goods&methods=blog&billingInternalProductSeq=11884168&productRegisterAreaGroupSeq=78&serviceSectionSeq=600",
        "image_url": "https://img.danawa.com/prod_img/500000/168/884/img/11884168_1.jpg",
        "registration_date": "등록월 2020.07."
    },
    {
        "prod_id": 53783246,
        "name": "앱코 U30 마린 (화이트)",
        "price": 45000,
        "specs": [
            "PC케이스(ATX)",
            "미들타워",
            "파워미포함",
            "ATX",
            "M-ATX",
            "M-ITX",
            "쿨링팬:총3개",
            "LED팬:3개",
            "전면 패널 타입:강화유리",
            "측면 패널 타입:강화유리",
            "측면 개폐 방식:버튼",
            "후면:120mm LED x1",
            "내부 측면:120mm LED x2",
            "너비(W):212mm",
            "깊이(D):420mm",
            "높이(H):485mm",
            "파워 장착 길이:240mm",
            "파워 위치:하단후면",
            "VGA 장착 길이:400mm",
            "CPU쿨러 장착높이:165mm",
            "LED 색상:RGB"
        ],
        "danawa_href": "https://shop.danawa.com/main/?controller=goods&methods=blog&billingInternalProductSeq=53783246&productRegisterAreaGroupSeq=78&serviceSectionSeq=600",
        "image_url": "https://img.danawa.com/prod_img/500000/246/783/img/53783246_1.jpg",
        "registration_date": "등록월 2024.05."
    },
    {
        "prod_id": 10423167,
        "name": "마이크로닉스 Master M60 메쉬 (블랙)",
        "price": 45500,
        "specs": [
            "PC케이스(ATX)",
            "미들타워",
            "파워미포함",
            "ATX",
            "M-ATX",
            "M-ITX",
            "쿨링팬:총6개",
            "LED팬:4개",
            "전면 패널 타입:메쉬",
            "측면 패널 타입:강화유리",
            "측면 개폐 방식:스윙도어",
            "후면:120mm LED x1",
            "전면:120mm LED x3",
            "상단:120mm x2",
            "너비(W):221mm",
            "깊이(D):390mm",
            "높이(H):461mm",
            "파워 장착 길이:190mm",
            "파워 위치:하단후면",
            "VGA 장착 길이:325mm",
            "CPU쿨러 장착높이:175mm",
            "RGB 컨트롤",
            "LED 색상:RGB",
            "월2020년 4월 내부 새시 변경 / 2020년 9월 측면 재질 변경 (아크릴->강화유리) / 23년 7월 측면 개폐 방식 스윙도어로 변경"
        ],
        "danawa_href": "https://shop.danawa.com/main/?controller=goods&methods=blog&billingInternalProductSeq=10423167&productRegisterAreaGroupSeq=78&serviceSectionSeq=600",
        "image_url": "https://img.danawa.com/prod_img/500000/167/423/img/10423167_1.jpg",
        "registration_date": "등록월 2020.01."
    },
    {
        "prod_id": 33439418,
        "name": "Antec C8 MESH (화이트)",
        "price": 130390,
        "specs": [
            "PC케이스(ATX)",
            "빅타워",
            "파워미포함",
            "E-ATX",
            "ATX",
            "M-ATX",
            "ITX",
            "수직 PCI형태:슬롯변경형",
            "전면 패널 타입:강화유리",
            "측면 패널 타입:강화유리",
            "너비(W):303mm",
            "깊이(D):464mm",
            "높이(H):476mm",
            "파워 장착 길이:210mm",
            "VGA 장착 길이:440mm",
            "CPU쿨러 장착높이:175mm"
        ],
        "danawa_href": "https://shop.danawa.com/main/?controller=goods&methods=blog&billingInternalProductSeq=33439418&productRegisterAreaGroupSeq=78&serviceSectionSeq=600",
        "image_url": "https://img.danawa.com/prod_img/500000/418/439/img/33439418_1.jpg",
        "registration_date": "등록월 2024.01."
    },
    {
        "prod_id": 16542008,
        "name": "darkFlash DK1000 MESH 강화유리 (블랙)",
        "price": 68000,
        "specs": [
            "PC케이스(ATX)",
            "미들타워",
            "파워미포함",
            "E-ATX",
            "ATX",
            "M-ATX",
            "쿨링팬:총4개",
            "전면 패널 타입:메쉬",
            "측면 패널 타입:강화유리",
            "후면:120mm x1",
            "전면:140mm x3",
            "너비(W):215mm",
            "깊이(D):415mm",
            "높이(H):470mm",
            "파워 장착 길이:245mm",
            "VGA 장착 길이:355mm",
            "CPU쿨러 장착높이:165mm",
            "오픈도어"
        ],
        "danawa_href": "https://shop.danawa.com/main/?controller=goods&methods=blog&billingInternalProductSeq=16542008&productRegisterAreaGroupSeq=78&serviceSectionSeq=600",
        "image_url": "https://img.danawa.com/prod_img/500000/008/542/img/16542008_1.jpg",
        "registration_date": "등록월 2022.03."
    },
    {
        "prod_id": 68441162,
        "name": "DAVEN AQUA 스쿠버 ARGB BTF (블랙)",
        "price": 49900,
        "specs": [
            "PC케이스(ATX)",
            "미들타워",
            "파워미포함",
            "E-ATX",
            "ATX",
            "ATX (후면커넥터)",
            "M-ATX",
            "M-ATX (후면커넥터)",
            "M-ITX",
            "쿨링팬:총4개",
            "LED팬:4개",
            "전면 패널 타입:강화유리",
            "측면 패널 타입:강화유리",
            "후면:120mm LED x1",
            "내부 측면:120mm LED x3",
            "너비(W):220mm",
            "깊이(D):444mm",
            "높이(H):490mm",
            "파워 장착 길이:220mm",
            "파워 위치:하단후면",
            "VGA 장착 길이:440mm",
            "CPU쿨러 장착높이:175mm",
            "LED 색상:ARGB"
        ],
        "danawa_href": "https://shop.danawa.com/main/?controller=goods&methods=blog&billingInternalProductSeq=68441162&productRegisterAreaGroupSeq=78&serviceSectionSeq=600",
        "image_url": "https://img.danawa.com/prod_img/500000/162/441/img/68441162_1.jpg",
        "registration_date": "등록월 2024.10."
    },
    {
        "prod_id": 47489189,
        "name": "컴이지 킹덤 비바리움 미니 (화이트)",
        "price": 33500,
        "specs": [
            "PC케이스(M-ATX)",
            "미니타워",
            "파워미포함",
            "M-ATX",
            "M-ITX",
            "쿨링팬:총3개",
            "LED팬:3개",
            "전면 패널 타입:강화유리",
            "측면 패널 타입:강화유리",
            "후면:120mm LED x1",
            "내부 측면:120mm LED x2",
            "너비(W):212mm",
            "깊이(D):365mm이상",
            "높이(H):435mm",
            "파워 장착 길이:180~220mm",
            "파워 위치:하단후면",
            "VGA 장착 길이:350mm",
            "CPU쿨러 장착높이:165mm",
            "LED 색상:화이트"
        ],
        "danawa_href": "https://shop.danawa.com/main/?controller=goods&methods=blog&billingInternalProductSeq=47489189&productRegisterAreaGroupSeq=78&serviceSectionSeq=600",
        "image_url": "https://img.danawa.com/prod_img/500000/189/489/img/47489189_1.jpg",
        "registration_date": "등록월 2024.04."
    },
    {
        "prod_id": 40016375,
        "name": "Fractal Design North XL MESH (차콜 블랙)",
        "price": 299010,
        "specs": [
            "PC케이스(ATX)",
            "빅타워",
            "파워미포함",
            "E-ATX",
            "ATX",
            "M-ATX",
            "M-ITX",
            "쿨링팬:총3개",
            "측면 패널 타입:통풍구",
            "전면:140mm x3",
            "너비(W):240mm",
            "깊이(D):503mm",
            "높이(H):509mm",
            "파워 장착 길이:290mm",
            "VGA 장착 길이:413mm",
            "CPU쿨러 장착높이:185mm",
            "팬 컨트롤"
        ],
        "danawa_href": "https://shop.danawa.com/main/?controller=goods&methods=blog&billingInternalProductSeq=40016375&productRegisterAreaGroupSeq=78&serviceSectionSeq=600",
        "image_url": "https://img.danawa.com/prod_img/500000/375/016/img/40016375_1.jpg",
        "registration_date": "등록월 2024.03."
    },
    {
        "prod_id": 31412510,
        "name": "앱코 O10M 오피스 라이트 (블랙)",
        "price": 16800,
        "specs": [
            "PC케이스(M-ATX)",
            "미니타워",
            "파워미포함",
            "M-ATX",
            "M-ITX",
            "쿨링팬:총1개",
            "전면 패널 타입:일반(솔리드)",
            "측면 패널 타입:통풍구",
            "후면:80mm x1",
            "너비(W):160mm",
            "깊이(D):284mm",
            "높이(H):350mm",
            "파워 장착 길이:250mm",
            "파워 위치:상단",
            "VGA 장착 길이:260mm",
            "CPU쿨러 장착높이:135mm"
        ],
        "danawa_href": "https://shop.danawa.com/main/?controller=goods&methods=blog&billingInternalProductSeq=31412510&productRegisterAreaGroupSeq=78&serviceSectionSeq=600",
        "image_url": "https://img.danawa.com/prod_img/500000/510/412/img/31412510_1.jpg",
        "registration_date": "등록월 2023.12."
    },
    {
        "prod_id": 62791454,
        "name": "마이크로닉스 WIZMAX ML-360 WIDE View BTF (블랙)",
        "price": 104000,
        "specs": [
            "PC케이스(ATX)",
            "미들타워",
            "파워미포함",
            "ATX",
            "ATX (후면커넥터)",
            "M-ATX",
            "M-ATX (후면커넥터)",
            "ITX",
            "쿨링팬:총4개",
            "LED팬:4개",
            "전면 패널 타입:강화유리",
            "측면 패널 타입:강화유리",
            "후면:140mm LED x1",
            "내부 측면:120mm LED x3",
            "너비(W):238mm",
            "깊이(D):456mm",
            "높이(H):500mm",
            "파워 위치:하단후면",
            "VGA 장착 길이:430mm",
            "CPU쿨러 장착높이:180mm",
            "RGB 컨트롤",
            "LED 색상:ARGB"
        ],
        "danawa_href": "https://shop.danawa.com/main/?controller=goods&methods=blog&billingInternalProductSeq=62791454&productRegisterAreaGroupSeq=78&serviceSectionSeq=600",
        "image_url": "https://img.danawa.com/prod_img/500000/454/791/img/62791454_1.jpg",
        "registration_date": "등록월 2024.08."
    },
    {
        "prod_id": 11884207,
        "name": "darkFlash DLX21 RGB MESH 강화유리 (화이트)",
        "price": 99000,
        "specs": [
            "PC케이스(ATX)",
            "미들타워",
            "파워미포함",
            "E-ATX",
            "ATX",
            "M-ATX",
            "M-ITX",
            "쿨링팬:총4개",
            "LED팬:4개",
            "측면 패널 타입:강화유리",
            "측면 개폐 방식:스윙도어",
            "후면:140mm LED x1",
            "전면:140mm LED x3",
            "너비(W):233mm",
            "깊이(D):448mm",
            "높이(H):493mm",
            "파워 장착 길이:235mm",
            "파워 위치:하단후면",
            "VGA 장착 길이:400mm",
            "CPU쿨러 장착높이:180mm",
            "RGB 컨트롤",
            "LED 색상:RGB"
        ],
        "danawa_href": "https://shop.danawa.com/main/?controller=goods&methods=blog&billingInternalProductSeq=11884207&productRegisterAreaGroupSeq=78&serviceSectionSeq=600",
        "image_url": "https://img.danawa.com/prod_img/500000/207/884/img/11884207_1.jpg",
        "registration_date": "등록월 2020.07."
    },
    {
        "prod_id": 72723491,
        "name": "darkFlash DCM30 RGB 강화유리 (블랙)",
        "price": 29500,
        "specs": [
            "PC케이스(ATX)",
            "미니타워",
            "파워미포함",
            "M-ATX",
            "M-ITX",
            "쿨링팬:총3개",
            "LED팬:3개",
            "전면 패널 타입:강화유리",
            "측면 패널 타입:강화유리",
            "후면:120mm",
            "내부 측면:120mm",
            "너비(W):275mm",
            "깊이(D):333mm",
            "높이(H):323mm",
            "파워 장착 길이:160mm",
            "파워 위치:하단후면",
            "VGA 장착 길이:325mm",
            "CPU쿨러 장착높이:155mm",
            "LED 색상:RGB"
        ],
        "danawa_href": "https://shop.danawa.com/main/?controller=goods&methods=blog&billingInternalProductSeq=72723491&productRegisterAreaGroupSeq=78&serviceSectionSeq=600",
        "image_url": "https://img.danawa.com/prod_img/500000/491/723/img/72723491_1.jpg",
        "registration_date": "등록월 2024.12."
    },
    {
        "prod_id": 17192498,
        "name": "잘만 Z10 PLUS (블랙)",
        "price": 94500,
        "specs": [
            "PC케이스(ATX)",
            "미들타워",
            "파워미포함",
            "E-ATX",
            "ATX",
            "M-ATX",
            "M-ITX",
            "쿨링팬:총4개",
            "LED팬:4개",
            "전면 패널 타입:메쉬",
            "측면 패널 타입:강화유리",
            "측면 개폐 방식:스윙도어",
            "후면:120mm LED x1",
            "전면:140mm LED x3",
            "너비(W):220mm",
            "깊이(D):481mm",
            "높이(H):488mm",
            "파워 장착 길이:200mm",
            "파워 위치:하단후면",
            "VGA 장착 길이:395mm",
            "CPU쿨러 장착높이:173mm",
            "외부LED 컨트롤",
            "LED 색상:ARGB",
            "그래픽카드 지지대 기본 제공 / ※ 9월 26일자 측면 스윙도어 업그레이드"
        ],
        "danawa_href": "https://shop.danawa.com/main/?controller=goods&methods=blog&billingInternalProductSeq=17192498&productRegisterAreaGroupSeq=78&serviceSectionSeq=600",
        "image_url": "https://img.danawa.com/prod_img/500000/498/192/img/17192498_1.jpg",
        "registration_date": "등록월 2022.06."
    },
    {
        "prod_id": 57709235,
        "name": "3RSYS L904 Quiet (블랙)",
        "price": 89000,
        "specs": [
            "PC케이스(ATX)",
            "미들타워",
            "파워미포함",
            "ATX",
            "M-ATX",
            "ITX",
            "쿨링팬:총4개",
            "전면 패널 타입:일반(솔리드)",
            "측면 패널 타입:강철",
            "후면:120mm x1",
            "전면:120mm x3",
            "너비(W):230mm",
            "깊이(D):457mm",
            "높이(H):490mm",
            "파워 장착 길이:200mm",
            "파워 위치:하단후면",
            "VGA 장착 길이:400mm",
            "CPU쿨러 장착높이:180mm"
        ],
        "danawa_href": "https://shop.danawa.com/main/?controller=goods&methods=blog&billingInternalProductSeq=57709235&productRegisterAreaGroupSeq=78&serviceSectionSeq=600",
        "image_url": "https://img.danawa.com/prod_img/500000/235/709/img/57709235_1.jpg",
        "registration_date": "등록월 2024.06."
    },
    {
        "prod_id": 72224177,
        "name": "마이크로닉스 WIZMAX 오로라 (블랙)",
        "price": 23000,
        "specs": [
            "PC케이스(M-ATX)",
            "미니타워",
            "파워미포함",
            "M-ATX",
            "ITX",
            "쿨링팬:총2개",
            "측면 패널 타입:통풍구",
            "후면:120mm x1",
            "전면:120mm x1",
            "너비(W):180mm",
            "깊이(D):297mm",
            "높이(H):357mm",
            "파워 위치:상단",
            "VGA 장착 길이:250mm",
            "CPU쿨러 장착높이:157mm",
            "외부 LED"
        ],
        "danawa_href": "https://shop.danawa.com/main/?controller=goods&methods=blog&billingInternalProductSeq=72224177&productRegisterAreaGroupSeq=78&serviceSectionSeq=600",
        "image_url": "https://img.danawa.com/prod_img/500000/177/224/img/72224177_1.jpg",
        "registration_date": "등록월 2024.12."
    },
    {
        "prod_id": 72470105,
        "name": "Antec FLUX PRO MESH (블랙)",
        "price": 249000,
        "specs": [
            "PC케이스(ATX)",
            "빅타워",
            "파워미포함",
            "E-ATX",
            "ATX",
            "M-ATX",
            "ITX",
            "쿨링팬:총6개",
            "전면 패널 타입:메쉬",
            "측면 패널 타입:강화유리",
            "후면:140mm x1",
            "전면:140mm x3",
            "하단:120mm x2",
            "너비(W):245mm",
            "깊이(D):530mm",
            "높이(H):545mm",
            "파워 장착 길이:180~300mm",
            "파워 위치:하단후면",
            "VGA 장착 길이:455mm",
            "CPU쿨러 장착높이:190mm",
            "팬 컨트롤",
            "RGB 컨트롤"
        ],
        "danawa_href": "https://shop.danawa.com/main/?controller=goods&methods=blog&billingInternalProductSeq=72470105&productRegisterAreaGroupSeq=78&serviceSectionSeq=600",
        "image_url": "https://img.danawa.com/prod_img/500000/105/470/img/72470105_1.jpg",
        "registration_date": "등록월 2024.12."
    },
    {
        "prod_id": 65426303,
        "name": "DAVEN AQUA 다이버 (블랙)",
        "price": 37900,
        "specs": [
            "PC케이스(ATX)",
            "미들타워",
            "파워미포함",
            "E-ATX",
            "ATX",
            "M-ATX",
            "M-ITX",
            "쿨링팬:총3개",
            "LED팬:3개",
            "전면 패널 타입:강화유리",
            "측면 패널 타입:강화유리",
            "측면 개폐 방식:버튼",
            "후면:120mm LED x1",
            "내부 측면:120mm LED x2",
            "너비(W):215mm",
            "깊이(D):425mm",
            "높이(H):490mm",
            "파워 장착 길이:220mm",
            "파워 위치:하단후면",
            "VGA 장착 길이:400mm",
            "CPU쿨러 장착높이:165mm",
            "LED 색상:RGB"
        ],
        "danawa_href": "https://shop.danawa.com/main/?controller=goods&methods=blog&billingInternalProductSeq=65426303&productRegisterAreaGroupSeq=78&serviceSectionSeq=600",
        "image_url": "https://img.danawa.com/prod_img/500000/303/426/img/65426303_1.jpg",
        "registration_date": "등록월 2024.09."
    }
]